{"title":"In Age And Sadness - Tragedy Of The Commons - 2004","uid":9404688,"size":58876692,"categoryP":"audio","categoryS":"music","magnet":"?xt=urn:btih:0b10cf617d18b8b5b3bbd970131fc5f7c57b03fb&amp;dn=In+Age+And+Sadness+-+Tragedy+Of+The+Commons+-+2004&amp;tr=udp%3A%2F%2Ftracker.openbittorrent.com%3A80&amp;tr=udp%3A%2F%2Fopen.demonii.com%3A1337&amp;tr=udp%3A%2F%2Ftracker.coppersurfer.tk%3A6969&amp;tr=udp%3A%2F%2Fexodus.desync.com%3A6969","seeders":1,"leechers":0,"uploader":"CoenV","files":4,"time":1388134462,"description":"320 CBR","torrent":{"xt":"urn:btih:0b10cf617d18b8b5b3bbd970131fc5f7c57b03fb","amp;dn":"In+Age+And+Sadness+-+Tragedy+Of+The+Commons+-+2004","amp;tr":["udp%3A%2F%2Ftracker.openbittorrent.com%3A80","udp%3A%2F%2Fopen.demonii.com%3A1337","udp%3A%2F%2Ftracker.coppersurfer.tk%3A6969","udp%3A%2F%2Fexodus.desync.com%3A6969"],"infoHash":"0b10cf617d18b8b5b3bbd970131fc5f7c57b03fb","infoHashBuffer":{"type":"Buffer","data":[11,16,207,97,125,24,184,181,179,187,217,112,19,31,197,247,197,123,3,251]},"announce":[],"urlList":[]}}