{"title":"25 Hot Angelina Jolie Wallpaper Set 14","uid":12811537,"size":17451229,"categoryP":"other","categoryS":"pictures","magnet":"?xt=urn:btih:1075d4cdfbf4b084cbcedca1bc82711f2d175b8d&amp;dn=25+Hot+Angelina+Jolie+Wallpaper+Set+14&amp;tr=udp%3A%2F%2Ftracker.leechers-paradise.org%3A6969&amp;tr=udp%3A%2F%2Fzer0day.ch%3A1337&amp;tr=udp%3A%2F%2Fopen.demonii.com%3A1337&amp;tr=udp%3A%2F%2Ftracker.coppersurfer.tk%3A6969&amp;tr=udp%3A%2F%2Fexodus.desync.com%3A6969","seeders":1,"leechers":0,"uploader":"sodebabe","files":27,"time":1448188181,"description":"[b]25 Hot Angelina Jolie Wallpaper Set 14\r\n\r\n25 JPG    |    mix    | 16 Mb [/b]","torrent":{"xt":"urn:btih:1075d4cdfbf4b084cbcedca1bc82711f2d175b8d","amp;dn":"25+Hot+Angelina+Jolie+Wallpaper+Set+14","amp;tr":["udp%3A%2F%2Ftracker.leechers-paradise.org%3A6969","udp%3A%2F%2Fzer0day.ch%3A1337","udp%3A%2F%2Fopen.demonii.com%3A1337","udp%3A%2F%2Ftracker.coppersurfer.tk%3A6969","udp%3A%2F%2Fexodus.desync.com%3A6969"],"infoHash":"1075d4cdfbf4b084cbcedca1bc82711f2d175b8d","infoHashBuffer":{"type":"Buffer","data":[16,117,212,205,251,244,176,132,203,206,220,161,188,130,113,31,45,23,91,141]},"announce":[],"urlList":[]}}