{"title":"Snitch","uid":8816649,"size":734519296,"categoryP":"video","categoryS":"movies","magnet":"?xt=urn:btih:1421a62ec8f753122946925a4029508ca11af653&amp;dn=Snitch&amp;tr=udp%3A%2F%2Ftracker.openbittorrent.com%3A80&amp;tr=udp%3A%2F%2Fopen.demonii.com%3A1337&amp;tr=udp%3A%2F%2Ftracker.coppersurfer.tk%3A6969&amp;tr=udp%3A%2F%2Fexodus.desync.com%3A6969","seeders":1,"leechers":0,"uploader":"cj48089","files":-1,"time":1376602227,"description":"Snitch (2013)\n\nA father goes undercover for the DEA in order to free his son who was imprisoned after being set up in a drug deal.","torrent":{"xt":"urn:btih:1421a62ec8f753122946925a4029508ca11af653","amp;dn":"Snitch","amp;tr":["udp%3A%2F%2Ftracker.openbittorrent.com%3A80","udp%3A%2F%2Fopen.demonii.com%3A1337","udp%3A%2F%2Ftracker.coppersurfer.tk%3A6969","udp%3A%2F%2Fexodus.desync.com%3A6969"],"infoHash":"1421a62ec8f753122946925a4029508ca11af653","infoHashBuffer":{"type":"Buffer","data":[20,33,166,46,200,247,83,18,41,70,146,90,64,41,80,140,161,26,246,83]},"announce":[],"urlList":[]}}