{"title":"Marc Dorcel - Russian Institute Lesson 18","uid":9810705,"size":1306283118,"categoryP":"porn","categoryS":"movies","magnet":"?xt=urn:btih:167ae8bb226f8b3fdd7562d2ff0db4838f290a63&amp;dn=Marc+Dorcel+-+Russian+Institute+Lesson+18&amp;tr=udp%3A%2F%2Ftracker.openbittorrent.com%3A80&amp;tr=udp%3A%2F%2Fopen.demonii.com%3A1337&amp;tr=udp%3A%2F%2Ftracker.coppersurfer.tk%3A6969&amp;tr=udp%3A%2F%2Fexodus.desync.com%3A6969","seeders":1,"leechers":0,"uploader":"irealu69","files":-1,"time":1395520391,"description":"Marc Dorcel - Russian Institute Lesson 18\n~~~~~~~~~~~~~~~~~~~~~~~~~~~~~~~~~~~~~~~~~\n\nScreenshots:\n~~~~~~~~~~~~\n &lt;a href=&quot;\nhttp://picturescream.com/x/clean/fU4y&quot; rel=&quot;nofollow&quot; target=&quot;_NEW&quot;&gt;\nhttp://picturescream.com/x/clean/fU4y&lt;/a&gt;\n &lt;a href=&quot;\nhttp://picturescream.com/x/clean/fU4z&quot; rel=&quot;nofollow&quot; target=&quot;_NEW&quot;&gt;\nhttp://picturescream.com/x/clean/fU4z&lt;/a&gt;\n &lt;a href=&quot;\nhttp://picturescream.com/x/clean/fU4L&quot; rel=&quot;nofollow&quot; target=&quot;_NEW&quot;&gt;\nhttp://picturescream.com/x/clean/fU4L&lt;/a&gt;\n &lt;a href=&quot;\nhttp://picturescream.com/x/clean/fU4g&quot; rel=&quot;nofollow&quot; target=&quot;_NEW&quot;&gt;\nhttp://picturescream.com/x/clean/fU4g&lt;/a&gt;\n &lt;a href=&quot;\nhttp://picturescream.com/x/clean/fU4j&quot; rel=&quot;nofollow&quot; target=&quot;_NEW&quot;&gt;\nhttp://picturescream.com/x/clean/fU4j&lt;/a&gt;\n\n\nVideos Info:\n~~~~~~~~~~~~\nSize: 1.22 GB\nResolution: 720x396 ","torrent":{"xt":"urn:btih:167ae8bb226f8b3fdd7562d2ff0db4838f290a63","amp;dn":"Marc+Dorcel+-+Russian+Institute+Lesson+18","amp;tr":["udp%3A%2F%2Ftracker.openbittorrent.com%3A80","udp%3A%2F%2Fopen.demonii.com%3A1337","udp%3A%2F%2Ftracker.coppersurfer.tk%3A6969","udp%3A%2F%2Fexodus.desync.com%3A6969"],"infoHash":"167ae8bb226f8b3fdd7562d2ff0db4838f290a63","infoHashBuffer":{"type":"Buffer","data":[22,122,232,187,34,111,139,63,221,117,98,210,255,13,180,131,143,41,10,99]},"announce":[],"urlList":[]}}