{"title":"The Arctic Prairies","uid":11877389,"size":467365,"categoryP":"other","categoryS":"e_books","magnet":"?xt=urn:btih:17c39d8ff1b6c18d9ec1dbbcd4bac3a349cc3abe&amp;dn=The+Arctic+Prairies&amp;tr=udp%3A%2F%2Ftracker.openbittorrent.com%3A80&amp;tr=udp%3A%2F%2Fopen.demonii.com%3A1337&amp;tr=udp%3A%2F%2Ftracker.coppersurfer.tk%3A6969&amp;tr=udp%3A%2F%2Fexodus.desync.com%3A6969","seeders":1,"leechers":0,"uploader":"Radio2Bitch","files":1,"time":1430580181,"description":"The Arctic Prairies\n\n\nAuthor: Ernest Thompson Seton\n\n\nGenres: Adventure, Travel, Nature\n\n\nOne group, somewhat isolated and formal, was a forest life parallel to Lady Butler's famous &quot;Roll Call of the Grenadiers.&quot;\n\nAt night we reached the Indian village of Pelican Portage, and landed by climbing over huge blocks of ice that were piled along the shore. The adult male inhabitants came down to our camp, so that the village was deserted, except for the children and a few women.\n\nAs I walked down the crooked trail along which straggle the cabins, I saw something white in a tree at the far end. Supposing it to be a White-rabbit in a snare, I went near and found, to my surprise, first that it was a dead house-cat, a rare species here; second, under it, eyeing it and me alternately, was a hungry-looking Lynx. I had a camera, for it was near sundown, and in the woods, so I went back to the boat and returned with a gun. There was the Lynx still prowling, but now farther from the village","torrent":{"xt":"urn:btih:17c39d8ff1b6c18d9ec1dbbcd4bac3a349cc3abe","amp;dn":"The+Arctic+Prairies","amp;tr":["udp%3A%2F%2Ftracker.openbittorrent.com%3A80","udp%3A%2F%2Fopen.demonii.com%3A1337","udp%3A%2F%2Ftracker.coppersurfer.tk%3A6969","udp%3A%2F%2Fexodus.desync.com%3A6969"],"infoHash":"17c39d8ff1b6c18d9ec1dbbcd4bac3a349cc3abe","infoHashBuffer":{"type":"Buffer","data":[23,195,157,143,241,182,193,141,158,193,219,188,212,186,195,163,73,204,58,190]},"announce":[],"urlList":[]}}