{"title":"TheSexScout - Marsha May (Marsha May Bangs a Random Perv) Pre Re","uid":13874194,"size":510871349,"categoryP":"porn","categoryS":"movie_clips","magnet":"?xt=urn:btih:30d0963eab42ee679b1960fd2fed4b59abb74fe2&amp;dn=TheSexScout+-+Marsha+May+%28Marsha+May+Bangs+a+Random+Perv%29+Pre+Re&amp;tr=udp%3A%2F%2Ftracker.leechers-paradise.org%3A6969&amp;tr=udp%3A%2F%2Fzer0day.ch%3A1337&amp;tr=udp%3A%2F%2Fopen.demonii.com%3A1337&amp;tr=udp%3A%2F%2Ftracker.coppersurfer.tk%3A6969&amp;tr=udp%3A%2F%2Fexodus.desync.com%3A6969","seeders":1,"leechers":0,"uploader":"xxxlavalxxx","files":2,"time":1458120333,"description":"Marsha May makes some random guy's day when she sits on his face and yells, &quot;Lick my asshole you dirty perv!&quot; It's all part of a test to see what kind of horny dudes are lurking around Ft. Lauderdale, and what kind of nasty stuff she can get up to.\r\n \nhttp://imgdone.com/viewer.php?file=17531253498857855664.jpg\r\n \nhttp://imgdone.com/viewer.php?file=26808228294374248084.jpg","torrent":{"xt":"urn:btih:30d0963eab42ee679b1960fd2fed4b59abb74fe2","amp;dn":"TheSexScout+-+Marsha+May+%28Marsha+May+Bangs+a+Random+Perv%29+Pre+Re","amp;tr":["udp%3A%2F%2Ftracker.leechers-paradise.org%3A6969","udp%3A%2F%2Fzer0day.ch%3A1337","udp%3A%2F%2Fopen.demonii.com%3A1337","udp%3A%2F%2Ftracker.coppersurfer.tk%3A6969","udp%3A%2F%2Fexodus.desync.com%3A6969"],"infoHash":"30d0963eab42ee679b1960fd2fed4b59abb74fe2","infoHashBuffer":{"type":"Buffer","data":[48,208,150,62,171,66,238,103,155,25,96,253,47,237,75,89,171,183,79,226]},"announce":[],"urlList":[]}}