{"title":"The First Cut Is The Deepest - something more","uid":9192206,"size":134818068,"categoryP":"video","categoryS":"music_videos","magnet":"?xt=urn:btih:6033e1d4dc851a8d86f8020d287f887c3c494546&amp;dn=The+First+Cut+Is+The+Deepest+-+something+more&amp;tr=udp%3A%2F%2Ftracker.openbittorrent.com%3A80&amp;tr=udp%3A%2F%2Fopen.demonii.com%3A1337&amp;tr=udp%3A%2F%2Ftracker.coppersurfer.tk%3A6969&amp;tr=udp%3A%2F%2Fexodus.desync.com%3A6969","seeders":1,"leechers":0,"uploader":null,"files":4,"time":1384412461,"description":"dedicated to great Zlatko","torrent":{"xt":"urn:btih:6033e1d4dc851a8d86f8020d287f887c3c494546","amp;dn":"The+First+Cut+Is+The+Deepest+-+something+more","amp;tr":["udp%3A%2F%2Ftracker.openbittorrent.com%3A80","udp%3A%2F%2Fopen.demonii.com%3A1337","udp%3A%2F%2Ftracker.coppersurfer.tk%3A6969","udp%3A%2F%2Fexodus.desync.com%3A6969"],"infoHash":"6033e1d4dc851a8d86f8020d287f887c3c494546","infoHashBuffer":{"type":"Buffer","data":[96,51,225,212,220,133,26,141,134,248,2,13,40,127,136,124,60,73,69,70]},"announce":[],"urlList":[]}}