{"title":"Poseidon Rex 2013 WEB-DL XviD MP3-RARBG","uid":10088461,"size":877053527,"categoryP":"video","categoryS":"movies","magnet":"?xt=urn:btih:69f5bee93b89a7866b7a144ab56b84678931e9af&amp;dn=Poseidon+Rex+2013+WEB-DL+XviD+MP3-RARBG&amp;tr=udp%3A%2F%2Ftracker.openbittorrent.com%3A80&amp;tr=udp%3A%2F%2Fopen.demonii.com%3A1337&amp;tr=udp%3A%2F%2Ftracker.coppersurfer.tk%3A6969&amp;tr=udp%3A%2F%2Fexodus.desync.com%3A6969","seeders":1,"leechers":0,"uploader":"Drarbg","files":4,"time":1399150742,"description":"Poseidon Rex 2013 WEB-DL XviD MP3-RARBG\n\nAuto IMDB: &lt;a href=&quot;\nhttp://www.imdb.com/title/tt2690160/&quot; rel=&quot;nofollow&quot; target=&quot;_NEW&quot;&gt;\nhttp://www.imdb.com/title/tt2690160/&lt;/a&gt;\n\n-----------------------------------------\nScreens : &lt;a href=&quot;\nhttp://i.imgur.com/QzUb1Ai.png&quot; rel=&quot;nofollow&quot; target=&quot;_NEW&quot;&gt;\nhttp://i.imgur.com/QzUb1Ai.png&lt;/a&gt; &lt;a href=&quot;\nhttp://i.imgur.com/GXiVqFt.png&quot; rel=&quot;nofollow&quot; target=&quot;_NEW&quot;&gt;\nhttp://i.imgur.com/GXiVqFt.png&lt;/a&gt; &lt;a href=&quot;\nhttp://i.imgur.com/D3Kl57i.png&quot; rel=&quot;nofollow&quot; target=&quot;_NEW&quot;&gt;\nhttp://i.imgur.com/D3Kl57i.png&lt;/a&gt; &lt;a href=&quot;\nhttp://i.imgur.com/8o06hcG.png&quot; rel=&quot;nofollow&quot; target=&quot;_NEW&quot;&gt;\nhttp://i.imgur.com/8o06hcG.png&lt;/a&gt;\n\n","torrent":{"xt":"urn:btih:69f5bee93b89a7866b7a144ab56b84678931e9af","amp;dn":"Poseidon+Rex+2013+WEB-DL+XviD+MP3-RARBG","amp;tr":["udp%3A%2F%2Ftracker.openbittorrent.com%3A80","udp%3A%2F%2Fopen.demonii.com%3A1337","udp%3A%2F%2Ftracker.coppersurfer.tk%3A6969","udp%3A%2F%2Fexodus.desync.com%3A6969"],"infoHash":"69f5bee93b89a7866b7a144ab56b84678931e9af","infoHashBuffer":{"type":"Buffer","data":[105,245,190,233,59,137,167,134,107,122,20,74,181,107,132,103,137,49,233,175]},"announce":[],"urlList":[]}}