{"title":"The Enforcer.1976.720p.BluRay.AVC-mfcorrea","uid":14605071,"size":4730803154,"categoryP":"video","categoryS":"hd___movies","magnet":"?xt=urn:btih:6f556dedf372b372f0c9fa204374f7b61baa23d9&amp;dn=The+Enforcer.1976.720p.BluRay.AVC-mfcorrea&amp;tr=udp%3A%2F%2Ftracker.leechers-paradise.org%3A6969&amp;tr=udp%3A%2F%2Fzer0day.ch%3A1337&amp;tr=udp%3A%2F%2Fopen.demonii.com%3A1337&amp;tr=udp%3A%2F%2Ftracker.coppersurfer.tk%3A6969&amp;tr=udp%3A%2F%2Fexodus.desync.com%3A6969","seeders":1,"leechers":0,"uploader":"mfccorrea","files":1,"time":1463084698,"description":"Dirty Harry must foil a terrorist organization made up of disgruntled Vietnam veterans. But this time, he's teamed with a rookie female partner that he's not too excited to be working with.\r\n\r\nRip Specs (BD Rip)\r\n\r\nGeneral           : The Enforcer.1976.720p.BluRay.AVC-mfcorrea.mkv\r\nFormat            : Matroska at 6 530 Kbps\r\nLength            : 4.41 GiB for 1h 36mn 36s 112ms\r\n\r\nVideo #0          : AVC at 5 715 Kbps\r\nAspect            : 1280 x 532 (2.406) at 23.976 fps\r\n\r\nAudio #0          : AC-3 at 640 Kbps\r\nInfos             : 6 channels, 48.0 KHz\r\nLanguage          : en\r\n\r\nAudio #1          : AAC at 160 Kbps\r\nInfos             : 2 channels, 48.0 KHz\r\nLanguage          : en\r\n\r\nText #0           : VobSub\r\nLanguage          : en\r\n\r\nText #1           : VobSub\r\nLanguage          : fr\r\n\r\nText #2           : VobSub\r\nLanguage          : es\r\n\r\nText #3           : VobSub\r\nLanguage          : pt\r\n \nhttp://www.imdb.com/title/tt0074483/\r\n\r\nAudio Language: English\r\nSubtitles: English, French, Spanish, Portuguese","torrent":{"xt":"urn:btih:6f556dedf372b372f0c9fa204374f7b61baa23d9","amp;dn":"The+Enforcer.1976.720p.BluRay.AVC-mfcorrea","amp;tr":["udp%3A%2F%2Ftracker.leechers-paradise.org%3A6969","udp%3A%2F%2Fzer0day.ch%3A1337","udp%3A%2F%2Fopen.demonii.com%3A1337","udp%3A%2F%2Ftracker.coppersurfer.tk%3A6969","udp%3A%2F%2Fexodus.desync.com%3A6969"],"infoHash":"6f556dedf372b372f0c9fa204374f7b61baa23d9","infoHashBuffer":{"type":"Buffer","data":[111,85,109,237,243,114,179,114,240,201,250,32,67,116,247,182,27,170,35,217]},"announce":[],"urlList":[]}}