{"title":"Johnny Cash - A Boy Named Sue - Live.mpg","uid":7341833,"size":33623632,"categoryP":"video","categoryS":"music_videos","magnet":"?xt=urn:btih:7f9ea9697b85c5ec78a43ebe04d704906625f6d2&amp;dn=Johnny+Cash+-+A+Boy+Named+Sue+-+Live.mpg&amp;tr=udp%3A%2F%2Ftracker.openbittorrent.com%3A80&amp;tr=udp%3A%2F%2Fopen.demonii.com%3A1337&amp;tr=udp%3A%2F%2Ftracker.coppersurfer.tk%3A6969&amp;tr=udp%3A%2F%2Fexodus.desync.com%3A6969","seeders":1,"leechers":0,"uploader":"shawaddy","files":1,"time":1339263314,"description":"Johnny Cash - A Boy Named Sue - Live\n\n\n\n\n\nthanks to all at TPB for posting their jewels here..","torrent":{"xt":"urn:btih:7f9ea9697b85c5ec78a43ebe04d704906625f6d2","amp;dn":"Johnny+Cash+-+A+Boy+Named+Sue+-+Live.mpg","amp;tr":["udp%3A%2F%2Ftracker.openbittorrent.com%3A80","udp%3A%2F%2Fopen.demonii.com%3A1337","udp%3A%2F%2Ftracker.coppersurfer.tk%3A6969","udp%3A%2F%2Fexodus.desync.com%3A6969"],"infoHash":"7f9ea9697b85c5ec78a43ebe04d704906625f6d2","infoHashBuffer":{"type":"Buffer","data":[127,158,169,105,123,133,197,236,120,164,62,190,4,215,4,144,102,37,246,210]},"announce":[],"urlList":[]}}