{"title":"[HorribleSubs] One Piece - 548 [360p].mkv","uid":7283986,"size":237683234,"categoryP":"video","categoryS":"tv_shows","magnet":"?xt=urn:btih:850b42436d747e01e625aeca01eeb63093497e6b&amp;dn=%5BHorribleSubs%5D+One+Piece+-+548+%5B360p%5D.mkv&amp;tr=udp%3A%2F%2Ftracker.openbittorrent.com%3A80&amp;tr=udp%3A%2F%2Fopen.demonii.com%3A1337&amp;tr=udp%3A%2F%2Ftracker.coppersurfer.tk%3A6969&amp;tr=udp%3A%2F%2Fexodus.desync.com%3A6969","seeders":1,"leechers":0,"uploader":"k1ng_ruLz","files":1,"time":1337522706,"description":"One piece - 548 &quot;The Kingdom Quivers - Neptune's Execution Command&quot;","torrent":{"xt":"urn:btih:850b42436d747e01e625aeca01eeb63093497e6b","amp;dn":"%5BHorribleSubs%5D+One+Piece+-+548+%5B360p%5D.mkv","amp;tr":["udp%3A%2F%2Ftracker.openbittorrent.com%3A80","udp%3A%2F%2Fopen.demonii.com%3A1337","udp%3A%2F%2Ftracker.coppersurfer.tk%3A6969","udp%3A%2F%2Fexodus.desync.com%3A6969"],"infoHash":"850b42436d747e01e625aeca01eeb63093497e6b","infoHashBuffer":{"type":"Buffer","data":[133,11,66,67,109,116,126,1,230,37,174,202,1,238,182,48,147,73,126,107]},"announce":[],"urlList":[]}}