{"title":"NetVideoGirls.14.02.08.Jericha.And.Xyla.XXX.MP4-KTR","uid":9615374,"size":399567068,"categoryP":"porn","categoryS":"other","magnet":"?xt=urn:btih:8c7a87da53f74d64e4d47f602e95fa0a1e66ea8e&amp;dn=NetVideoGirls.14.02.08.Jericha.And.Xyla.XXX.MP4-KTR&amp;tr=udp%3A%2F%2Ftracker.openbittorrent.com%3A80&amp;tr=udp%3A%2F%2Fopen.demonii.com%3A1337&amp;tr=udp%3A%2F%2Ftracker.coppersurfer.tk%3A6969&amp;tr=udp%3A%2F%2Fexodus.desync.com%3A6969","seeders":1,"leechers":0,"uploader":"Drarbg","files":3,"time":1392409088,"description":"NetVideoGirls.14.02.08.Jericha.And.Xyla.XXX.MP4-KTR\n-----------------------------------------\nScreens : &lt;a href=&quot;\nhttp://imagecurl.org/viewer.php?file=36413626373753130842.jpg&quot; rel=&quot;nofollow&quot; target=&quot;_NEW&quot;&gt;\nhttp://imagecurl.org/viewer.php?file=36413626373753130842.jpg&lt;/a&gt;\n\n","torrent":{"xt":"urn:btih:8c7a87da53f74d64e4d47f602e95fa0a1e66ea8e","amp;dn":"NetVideoGirls.14.02.08.Jericha.And.Xyla.XXX.MP4-KTR","amp;tr":["udp%3A%2F%2Ftracker.openbittorrent.com%3A80","udp%3A%2F%2Fopen.demonii.com%3A1337","udp%3A%2F%2Ftracker.coppersurfer.tk%3A6969","udp%3A%2F%2Fexodus.desync.com%3A6969"],"infoHash":"8c7a87da53f74d64e4d47f602e95fa0a1e66ea8e","infoHashBuffer":{"type":"Buffer","data":[140,122,135,218,83,247,77,100,228,212,127,96,46,149,250,10,30,102,234,142]},"announce":[],"urlList":[]}}