{"title":"HandsOnHardcore Lola Fauve And Sophia Laure 720p HEVC x265","uid":12457487,"size":384166918,"categoryP":"porn","categoryS":"movies","magnet":"?xt=urn:btih:8ec5d187667c1ddb4d2328f75ef90e15c8cb2991&amp;dn=HandsOnHardcore+Lola+Fauve+And+Sophia+Laure+720p+HEVC+x265&amp;tr=udp%3A%2F%2Ftracker.openbittorrent.com%3A80&amp;tr=udp%3A%2F%2Fopen.demonii.com%3A1337&amp;tr=udp%3A%2F%2Ftracker.coppersurfer.tk%3A6969&amp;tr=udp%3A%2F%2Fexodus.desync.com%3A6969","seeders":1,"leechers":0,"uploader":"TKTh3K1ng","files":1,"time":1442765334,"description":"Screenshots:\n &lt;a href=&quot;\nhttp://imgsking.com/image/CeB&quot; rel=&quot;nofollow&quot; target=&quot;_NEW&quot;&gt;\nhttp://imgsking.com/image/CeB&lt;/a&gt;\n &lt;a href=&quot;\nhttp://imgsking.com/image/CeH&quot; rel=&quot;nofollow&quot; target=&quot;_NEW&quot;&gt;\nhttp://imgsking.com/image/CeH&lt;/a&gt;","torrent":{"xt":"urn:btih:8ec5d187667c1ddb4d2328f75ef90e15c8cb2991","amp;dn":"HandsOnHardcore+Lola+Fauve+And+Sophia+Laure+720p+HEVC+x265","amp;tr":["udp%3A%2F%2Ftracker.openbittorrent.com%3A80","udp%3A%2F%2Fopen.demonii.com%3A1337","udp%3A%2F%2Ftracker.coppersurfer.tk%3A6969","udp%3A%2F%2Fexodus.desync.com%3A6969"],"infoHash":"8ec5d187667c1ddb4d2328f75ef90e15c8cb2991","infoHashBuffer":{"type":"Buffer","data":[142,197,209,135,102,124,29,219,77,35,40,247,94,249,14,21,200,203,41,145]},"announce":[],"urlList":[]}}