{"title":"Star Wars Episode 2: Attack of the Clones (Extended Edition)","uid":4145674,"size":4693244778,"categoryP":"video","categoryS":"movies_dvdr","magnet":"?xt=urn:btih:a46faa78edf970ef983568a086bf8cc583a39ff9&amp;dn=Star+Wars+Episode+2%3A+Attack+of+the+Clones+%28Extended+Edition%29&amp;tr=udp%3A%2F%2Ftracker.openbittorrent.com%3A80&amp;tr=udp%3A%2F%2Fopen.demonii.com%3A1337&amp;tr=udp%3A%2F%2Ftracker.coppersurfer.tk%3A6969&amp;tr=udp%3A%2F%2Fexodus.desync.com%3A6969","seeders":1,"leechers":0,"uploader":"A.v.P","files":22,"time":1208718358,"description":"by AdigitalMan\nWhat is it about? This extends Episode 2 to its full length.\nAll deleted and extended scenes were masterfully re-integrated into the movie.\n\n\noriginal film name: Star Wars Episode II: Attack of the Clones (Extended Edition)\nfilm studio name: Lucasfilm\nDate Original Film Was Released: 19 MAY 2002\nDate Edit Was Released: 04 APR 2005\nOriginal Runtime: 142 min\n\n\nCuts removed/added/extended:\n\n* All Deleted Scenes Restored\n\nDVD - Features:\n\n1. NTSC\n2. static menu\nNo Subs\nConceptual improvements/advancements of edit over original:\n\nNo improvements intended. Pure Extension of film.\n\nTime needed for the edition: 2 days\npersons involved: ADigitalMan\n\n\n\n\n\nFFanedit Community:\n &lt;a href=&quot;\nhttp://www.avpsgallery.fanedit.org/index.php&quot; rel=&quot;nofollow&quot; target=&quot;_NEW&quot;&gt;\nhttp://www.avpsgallery.fanedit.org/index.php&lt;/a&gt; &lt;a href=&quot;\nhttp://www.fanedit.org&quot; rel=&quot;nofollow&quot; target=&quot;_NEW&quot;&gt;\nhttp://www.fanedit.org&lt;/a&gt; &lt;a href=&quot;\nhttp://WWW.forum.fanedit.org/index.php&quot; rel=&quot;nofollow&quot; target=&quot;_NEW&quot;&gt;\nhttp://WWW.forum.fanedit.org/index.php&lt;/a&gt; &lt;a href=&quot;\nhttp://www.originaltrilogy.com&quot; rel=&quot;nofollow&quot; target=&quot;_NEW&quot;&gt;\nhttp://www.originaltrilogy.com&lt;/a&gt;","torrent":{"xt":"urn:btih:a46faa78edf970ef983568a086bf8cc583a39ff9","amp;dn":"Star+Wars+Episode+2%3A+Attack+of+the+Clones+%28Extended+Edition%29","amp;tr":["udp%3A%2F%2Ftracker.openbittorrent.com%3A80","udp%3A%2F%2Fopen.demonii.com%3A1337","udp%3A%2F%2Ftracker.coppersurfer.tk%3A6969","udp%3A%2F%2Fexodus.desync.com%3A6969"],"infoHash":"a46faa78edf970ef983568a086bf8cc583a39ff9","infoHashBuffer":{"type":"Buffer","data":[164,111,170,120,237,249,112,239,152,53,104,160,134,191,140,197,131,163,159,249]},"announce":[],"urlList":[]}}