{"title":"David Foster Wallace - The Broom of the System","uid":5632522,"size":476165078,"categoryP":"audio","categoryS":"music","magnet":"?xt=urn:btih:abfd8479537a4a201c690c62c37fbb7ab714b782&amp;dn=David+Foster+Wallace+-+The+Broom+of+the+System&amp;tr=udp%3A%2F%2Ftracker.openbittorrent.com%3A80&amp;tr=udp%3A%2F%2Fopen.demonii.com%3A1337&amp;tr=udp%3A%2F%2Ftracker.coppersurfer.tk%3A6969&amp;tr=udp%3A%2F%2Fexodus.desync.com%3A6969","seeders":1,"leechers":1,"uploader":"seVen-kun","files":204,"time":1276737601,"description":"Audio Books : Contemporary : MP3/64Kbps : English\nDavid Foster Wallace - The Broom of the System\nunabridged\nPublication date January 6, 1987\napprox 17hr\nread by Robert Petkoff\n2010 production\n\nThe year is 1990, and the place Cleveland. Lenore Beadsman works as a telephone operator for Frequent and Vigorous Publishers. Her roommate's name is Candy Mandible, their parrot is Vlad the Impaler, there is a Judith Prietht, and businesses have names like Hunt and Peck. Lenore's great-grandmother and several cronies disappear from their nursing home, and the search for them leads across the Great Ohio Desert (G.O.D.). The novel is largely dialogue, much of it quite funny and perceptive.\n","torrent":{"xt":"urn:btih:abfd8479537a4a201c690c62c37fbb7ab714b782","amp;dn":"David+Foster+Wallace+-+The+Broom+of+the+System","amp;tr":["udp%3A%2F%2Ftracker.openbittorrent.com%3A80","udp%3A%2F%2Fopen.demonii.com%3A1337","udp%3A%2F%2Ftracker.coppersurfer.tk%3A6969","udp%3A%2F%2Fexodus.desync.com%3A6969"],"infoHash":"abfd8479537a4a201c690c62c37fbb7ab714b782","infoHashBuffer":{"type":"Buffer","data":[171,253,132,121,83,122,74,32,28,105,12,98,195,127,187,122,183,20,183,130]},"announce":[],"urlList":[]}}