{"title":"WeLiveTogether.-.Sammie.Rhodes.Taylor.Vixen.Malena.Morgan","uid":6806282,"size":353091399,"categoryP":"porn","categoryS":"movies","magnet":"?xt=urn:btih:d037c83a9c4762b001f7980069ee6b325330cc57&amp;dn=WeLiveTogether.-.Sammie.Rhodes.Taylor.Vixen.Malena.Morgan&amp;tr=udp%3A%2F%2Ftracker.openbittorrent.com%3A80&amp;tr=udp%3A%2F%2Fopen.demonii.com%3A1337&amp;tr=udp%3A%2F%2Ftracker.coppersurfer.tk%3A6969&amp;tr=udp%3A%2F%2Fexodus.desync.com%3A6969","seeders":1,"leechers":7,"uploader":"exmnova","files":1,"time":1320874182,"description":"[WeLiveTogether./ RealityKings.] Sammie Rhodes, Taylor Vixen, Malena Morgan (Vivacious Vixen / 27 Oct 2011)\n\n\n &lt;a href=&quot;\nhttp://0.picswan.com/show.php/23737_1.jpg.html&quot; rel=&quot;nofollow&quot; target=&quot;_NEW&quot;&gt;\nhttp://0.picswan.com/show.php/23737_1.jpg.html&lt;/a&gt;\n\n\n\nMore Info:\n\n\n &lt;a href=&quot;\nhttp://www.69bits.com/torrent/Lesbian/40793/WeLiveTogether.-.Sammie.Rhodes.Taylor.Vixen.Malena.Morgan.html&quot; rel=&quot;nofollow&quot; target=&quot;_NEW&quot;&gt;\nhttp://www.69bits.com/torrent/Lesbian/40793/WeLiveTogether.-.Sammie.Rhodes.Taylor.Vixen.Malena.Morgan.html&lt;/a&gt;","torrent":{"xt":"urn:btih:d037c83a9c4762b001f7980069ee6b325330cc57","amp;dn":"WeLiveTogether.-.Sammie.Rhodes.Taylor.Vixen.Malena.Morgan","amp;tr":["udp%3A%2F%2Ftracker.openbittorrent.com%3A80","udp%3A%2F%2Fopen.demonii.com%3A1337","udp%3A%2F%2Ftracker.coppersurfer.tk%3A6969","udp%3A%2F%2Fexodus.desync.com%3A6969"],"infoHash":"d037c83a9c4762b001f7980069ee6b325330cc57","infoHashBuffer":{"type":"Buffer","data":[208,55,200,58,156,71,98,176,1,247,152,0,105,238,107,50,83,48,204,87]},"announce":[],"urlList":[]}}