{"title":"Redhead Teen Babe Love Huge Cocks.avi","uid":12475407,"size":398604764,"categoryP":"porn","categoryS":"movie_clips","magnet":"?xt=urn:btih:d42cd19927940e22bf12d1ce1002d372e4433ebd&amp;dn=Redhead+Teen+Babe+Love+Huge+Cocks.avi&amp;tr=udp%3A%2F%2Ftracker.openbittorrent.com%3A80&amp;tr=udp%3A%2F%2Fopen.demonii.com%3A1337&amp;tr=udp%3A%2F%2Ftracker.coppersurfer.tk%3A6969&amp;tr=udp%3A%2F%2Fexodus.desync.com%3A6969","seeders":1,"leechers":0,"uploader":"Piratepr0n","files":1,"time":1442970925,"description":"-------------------------------------------------------------------------------------\nName:\nRedhead Teen Babe Love Huge Cocks.avi\n-------------------------------------------------------------------------------------\nFile list:\nRedhead Teen Babe Love Huge Cocks.avi (380 MiB | 640x360 | 30min 50s | AVI) &lt;a href=&quot;\nhttp://imgfapper.com/img-5601e209712f6.html&quot; rel=&quot;nofollow&quot; target=&quot;_NEW&quot;&gt;\nhttp://imgfapper.com/img-5601e209712f6.html&lt;/a&gt;","torrent":{"xt":"urn:btih:d42cd19927940e22bf12d1ce1002d372e4433ebd","amp;dn":"Redhead+Teen+Babe+Love+Huge+Cocks.avi","amp;tr":["udp%3A%2F%2Ftracker.openbittorrent.com%3A80","udp%3A%2F%2Fopen.demonii.com%3A1337","udp%3A%2F%2Ftracker.coppersurfer.tk%3A6969","udp%3A%2F%2Fexodus.desync.com%3A6969"],"infoHash":"d42cd19927940e22bf12d1ce1002d372e4433ebd","infoHashBuffer":{"type":"Buffer","data":[212,44,209,153,39,148,14,34,191,18,209,206,16,2,211,114,228,67,62,189]},"announce":[],"urlList":[]}}