{"title":"Up[2009]DvDRip[Eng]-PiRaTeS","uid":6015504,"size":734119936,"categoryP":"video","categoryS":"movies","magnet":"?xt=urn:btih:e20e32fb4d56e97914e4c6672b7aa2d5ad5f50aa&amp;dn=Up%5B2009%5DDvDRip%5BEng%5D-PiRaTeS&amp;tr=udp%3A%2F%2Ftracker.openbittorrent.com%3A80&amp;tr=udp%3A%2F%2Fopen.demonii.com%3A1337&amp;tr=udp%3A%2F%2Ftracker.coppersurfer.tk%3A6969&amp;tr=udp%3A%2F%2Fexodus.desync.com%3A6969","seeders":1,"leechers":2,"uploader":"PiR4T3S","files":1,"time":1291624804,"description":"FILM DETAILS:\n\n\nLanguage        English\nDirected by\tPete Docter\nCo-Director:\n                Bob Peterson\nProduced by\tJonas Rivera\nExecutive Producers:\n                John Lasseter\n                Andrew Stanton\nScreenplay by\tBob Peterson\n                Pete Docter\nStory by\tPete Docter\n                Bob Peterson\n                Thomas McCarthy\nStarring\tEdward Asner\n                Christopher Plummer\n                Jordan Nagai\n                Bob Peterson\nMusic by\tMichael Giacchino\nEditing by\tKevin Nolting\nStudio\tPixar Animation Studios\nDistributed by\tWalt Disney Pictures\nRelease date(s)\tMay 29, 2009\nRunning time\t1:36:37\n\nPLOT:\n\nBy tying thousands of balloon to his home, 78-year-old Carl Fredricksen sets out to fulfill his lifelong dream to see the wilds of South America. Right after lifting off, however, he learns he isn't alone on his journey, since Russell, a wilderness explorer 70 years his junior, has inadvertently become a stowaway on the trip.","torrent":{"xt":"urn:btih:e20e32fb4d56e97914e4c6672b7aa2d5ad5f50aa","amp;dn":"Up%5B2009%5DDvDRip%5BEng%5D-PiRaTeS","amp;tr":["udp%3A%2F%2Ftracker.openbittorrent.com%3A80","udp%3A%2F%2Fopen.demonii.com%3A1337","udp%3A%2F%2Ftracker.coppersurfer.tk%3A6969","udp%3A%2F%2Fexodus.desync.com%3A6969"],"infoHash":"e20e32fb4d56e97914e4c6672b7aa2d5ad5f50aa","infoHashBuffer":{"type":"Buffer","data":[226,14,50,251,77,86,233,121,20,228,198,103,43,122,162,213,173,95,80,170]},"announce":[],"urlList":[]}}