{"title":"Krystal Harris - Me &amp; My Piano [320 Kbps]","uid":9746194,"size":112985032,"categoryP":"audio","categoryS":"music","magnet":"?xt=urn:btih:e6c4fa7face5e43ab84091cf384f125d3ffcb4c7&amp;dn=Krystal+Harris+-+Me+%26amp%3B+My+Piano+%5B320+Kbps%5D&amp;tr=udp%3A%2F%2Ftracker.openbittorrent.com%3A80&amp;tr=udp%3A%2F%2Fopen.demonii.com%3A1337&amp;tr=udp%3A%2F%2Ftracker.coppersurfer.tk%3A6969&amp;tr=udp%3A%2F%2Fexodus.desync.com%3A6969","seeders":1,"leechers":0,"uploader":"shareislife","files":-1,"time":1394586243,"description":"1. Supergirl! (3:42)\n2. My Religion (4:23)\n3. Angel On My Shoulder (3:58)\n4. You're The Reason (3:49)\n5. Love Is A Beautiful Thing (3:36)\n6. ...or Someone Else Will (4:35)\n7. When You Hurt (4:03)\n8. 1/2 My Heart (4:30)\n9. Goodbye (4:35)\n10. Lead Me (3:18)\n11. Let Me Be Your Friend (3:40)\n12. Me &amp; My Piano (2:36)","torrent":{"xt":"urn:btih:e6c4fa7face5e43ab84091cf384f125d3ffcb4c7","amp;dn":"Krystal+Harris+-+Me+%26amp%3B+My+Piano+%5B320+Kbps%5D","amp;tr":["udp%3A%2F%2Ftracker.openbittorrent.com%3A80","udp%3A%2F%2Fopen.demonii.com%3A1337","udp%3A%2F%2Ftracker.coppersurfer.tk%3A6969","udp%3A%2F%2Fexodus.desync.com%3A6969"],"infoHash":"e6c4fa7face5e43ab84091cf384f125d3ffcb4c7","infoHashBuffer":{"type":"Buffer","data":[230,196,250,127,172,229,228,58,184,64,145,207,56,79,18,93,63,252,180,199]},"announce":[],"urlList":[]}}