{"title":"Emergo (2011)HDRiP NL subs[Divx]NLtoppers","uid":7349007,"size":722729911,"categoryP":"video","categoryS":"movies","magnet":"?xt=urn:btih:ef75eb0ff2afae05940fca25a78612a8d54e90c9&amp;dn=Emergo+%282011%29HDRiP+NL+subs%5BDivx%5DNLtoppers&amp;tr=udp%3A%2F%2Ftracker.openbittorrent.com%3A80&amp;tr=udp%3A%2F%2Fopen.demonii.com%3A1337&amp;tr=udp%3A%2F%2Ftracker.coppersurfer.tk%3A6969&amp;tr=udp%3A%2F%2Fexodus.desync.com%3A6969","seeders":1,"leechers":0,"uploader":"GusGuzz","files":-1,"time":1339529199,"description":"Emergo (2011)HDRiP NL subs[Divx]NLtoppers\n\nAlternatieve titel: Apartment 143\n\n\nSpanje\nHorror\n80 minuten\ngeregisseerd door Carles Torrens\nmet Kai Lennox, Michael O'Keefe en Rick Gonzalez\n\nSpanje\nHorror\n80 minuten\n\ngeregisseerd door Carles Torrens\nmet Kai Lennox, Michael O'Keefe en Rick Gonzalez\n\nEen team van paranormaal begaafden onderzoekt een serie van abnormale fenomenen die plaatsvinden in een nieuw appartement. Vreemde telefoongesprekken, geheimzinnige schaduwen, bijzondere lichtflitsen, vliegende objecten en ontploffende lampen zijn enkele van de gebeurtenissen die plaatsvinden terwijl ze alles vastleggen met moderne technologische apparatuur. Met behulp van infraroodbeelden, digitale fotografie, psychofonische opnames, bewegingsdetectoren en magnetisch veldsterktemeters probeert de groep contact te leggen met de andere kant, wat uitermate gevaarlijk wordt als ze het point of no return naderen.\n\nMovie..............: Apartment 143 \nGenre..............: Horror\nSource.............: Apartment 143 2011 720p HDRiP AC3-5 1 x264-SiC\nSIZE............: 700 MB\nFORM............: AVI\nVIDEO CODEC.....: XVID\nBREEDTE.........: 720\nHOOGTE..........: 304\nAUDIO...........: English DD5.1\nAUDIO CODE......: AC3 \nBITRATE.........: 448 \nCHANNELS........: 5\nSUBTITELS.......: Dutch (hardcoded) - Nederlands (Ingebakken)\nSubtitles.NL.......: Vertaald door Depositair, Oemoe en Suurtje Thnx Team, Good Job *****\nControle...........: Suurtje.\nBewerking+Resync...: Suurtje. \n &lt;a href=&quot;\nhttp://www.moviemeter.nl/film/81501&quot; rel=&quot;nofollow&quot; target=&quot;_NEW&quot;&gt;\nhttp://www.moviemeter.nl/film/81501&lt;/a&gt;\n &lt;a href=&quot;\nhttp://www.imdb.com/title/tt1757742/&quot; rel=&quot;nofollow&quot; target=&quot;_NEW&quot;&gt;\nhttp://www.imdb.com/title/tt1757742/&lt;/a&gt;\n\n\nHeeft u deze film gezien en wilt u ergens een recencie achterlaten?\n\nga dan eens naar http://www.pheunix.nl\n\nVeel plezier\n\nNLtopper Gus_Guzzler\n\n","torrent":{"xt":"urn:btih:ef75eb0ff2afae05940fca25a78612a8d54e90c9","amp;dn":"Emergo+%282011%29HDRiP+NL+subs%5BDivx%5DNLtoppers","amp;tr":["udp%3A%2F%2Ftracker.openbittorrent.com%3A80","udp%3A%2F%2Fopen.demonii.com%3A1337","udp%3A%2F%2Ftracker.coppersurfer.tk%3A6969","udp%3A%2F%2Fexodus.desync.com%3A6969"],"infoHash":"ef75eb0ff2afae05940fca25a78612a8d54e90c9","infoHashBuffer":{"type":"Buffer","data":[239,117,235,15,242,175,174,5,148,15,202,37,167,134,18,168,213,78,144,201]},"announce":[],"urlList":[]}}