{"title":"World War Z (multi-audio: en, fr, de, it, es, pt + multi-subs) 1","uid":9903371,"size":3392084257,"categoryP":"video","categoryS":"movies","magnet":"?xt=urn:btih:fd8af9b472a76f5bc447e2d0873da7f529193e84&amp;dn=World+War+Z+%28multi-audio%3A+en%2C+fr%2C+de%2C+it%2C+es%2C+pt+%2B+multi-subs%29+1&amp;tr=udp%3A%2F%2Ftracker.openbittorrent.com%3A80&amp;tr=udp%3A%2F%2Fopen.demonii.com%3A1337&amp;tr=udp%3A%2F%2Ftracker.coppersurfer.tk%3A6969&amp;tr=udp%3A%2F%2Fexodus.desync.com%3A6969","seeders":1,"leechers":0,"uploader":"galex-713","files":1,"time":1396806555,"description":"FullHD (1080p, x264) extended/unrated version of World War Z, with multiple audio (AAC) streams (English, French, German, Italian and Portuguese) and multiple (Arabic, Bulgarian, Bresilian, Danish, German, English, Spanish, Farsi/Persian, French, Greek, Indonesian, Italian, Japanese, Malay, Dutch, Norwegian, Portuguese, Slovenian, Albanian, Serbian, Swedish and Vietnamese) subtitles (MKV S/UTF-8) in an unique MKV file.\n","torrent":{"xt":"urn:btih:fd8af9b472a76f5bc447e2d0873da7f529193e84","amp;dn":"World+War+Z+%28multi-audio%3A+en%2C+fr%2C+de%2C+it%2C+es%2C+pt+%2B+multi-subs%29+1","amp;tr":["udp%3A%2F%2Ftracker.openbittorrent.com%3A80","udp%3A%2F%2Fopen.demonii.com%3A1337","udp%3A%2F%2Ftracker.coppersurfer.tk%3A6969","udp%3A%2F%2Fexodus.desync.com%3A6969"],"infoHash":"fd8af9b472a76f5bc447e2d0873da7f529193e84","infoHashBuffer":{"type":"Buffer","data":[253,138,249,180,114,167,111,91,196,71,226,208,135,61,167,245,41,25,62,132]},"announce":[],"urlList":[]}}